{"cameraMode":{"drawMode":0,"name":"Shaded","section":"Shading Mode"},"sceneLighting":true,"audioPlay":false,"sceneViewState":{"showFog":true,"showMaterialUpdate":false,"showSkybox":true,"showFlares":true,"showImageEffects":true,"showParticleSystems":true},"in2DMode":false,"pivot":{"x":35.910621643066409,"y":1.951423168182373,"z":29.33736801147461},"rotation":{"x":-0.002324296860024333,"y":0.9940135478973389,"z":-0.1070796549320221,"w":-0.021578898653388025},"size":2.2407755851745607,"orthographic":false}